{
  "_class": "text",
  "attributedString": {
    "_class": "attributedString",
    "attributes": [
      {
        "_class": "stringAttribute",
        "attributes": {
          "MSAttributedStringColorAttribute": {
            "_class": "color",
            "alpha": 1,
            "blue": 1,
            "green": 1,
            "red": 1
          },
          "MSAttributedStringFontAttribute": {
            "_class": "fontDescriptor",
            "attributes": {
              "name": "SFProDisplay-Regular",
              "size": 28
            }
          },
          "kerning": 0.3600000143051147,
          "paragraphStyle": {
            "_class": "paragraphStyle",
            "allowsDefaultTighteningForTruncation": 0,
            "maximumLineHeight": 32,
            "minimumLineHeight": 32
          }
        },
        "length": 27,
        "location": 0
      }
    ],
    "string": "Display 28pt / 32pt Regular"
  },
  "automaticallyDrawOnUnderlyingPath": false,
  "booleanOperation": 0,
  "clippingMaskMode": 0,
  "do_objectID": "B4ACC1BA-71DE-4B7E-8AF2-E37ED37CAED6",
  "dontSynchroniseWithSymbol": false,
  "exportOptions": {
    "_class": "exportOptions",
    "do_objectID": "EC8E45CF-F07E-4DC2-880E-F134094B0990",
    "exportFormats": [
    ],
    "includedLayerIds": [
    ],
    "layerOptions": 0,
    "shouldTrim": false
  },
  "frame": {
    "_class": "rect",
    "constrainProportions": false,
    "do_objectID": "990CCC56-7BEC-4EFD-821A-DEDE9A4B83B4",
    "height": 32,
    "width": 331,
    "x": 407,
    "y": 551
  },
  "glyphBounds": "{{1, 5}, {329, 27}}",
  "hasClippingMask": false,
  "isFixedToViewport": false,
  "isFlippedHorizontal": false,
  "isFlippedVertical": false,
  "isLocked": false,
  "isVisible": true,
  "layerListExpandedType": 0,
  "lineSpacingBehaviour": 2,
  "maintainScrollPosition": false,
  "name": "iOS/1.DISPLAY/Display 1 (28R)/∙ Left/textPrimarySpecial0",
  "nameIsFixed": true,
  "resizingConstraint": 9,
  "resizingType": 0,
  "rotation": 0,
  "sharedStyleID": "3ECA357A-51E7-41B2-96B5-68ECDC9F4C44",
  "shouldBreakMaskChain": false,
  "style": {
    "_class": "style",
    "blur": {
      "_class": "blur",
      "center": "{0.5, 0.5}",
      "isEnabled": false,
      "motionAngle": 0,
      "radius": 10,
      "saturation": 1,
      "type": 0
    },
    "borderOptions": {
      "_class": "borderOptions",
      "dashPattern": [
      ],
      "isEnabled": true,
      "lineCapStyle": 0,
      "lineJoinStyle": 0
    },
    "borders": [
    ],
    "colorControls": {
      "_class": "colorControls",
      "brightness": 0,
      "contrast": 1,
      "hue": 0,
      "isEnabled": true,
      "saturation": 1
    },
    "contextSettings": {
      "_class": "graphicsContextSettings",
      "blendMode": 0,
      "opacity": 1
    },
    "do_objectID": "B2458C12-010B-49E2-B7D0-1CF8E50CA4CA",
    "endMarkerType": 0,
    "fills": [
    ],
    "innerShadows": [
    ],
    "miterLimit": 10,
    "shadows": [
    ],
    "startMarkerType": 0,
    "textStyle": {
      "_class": "textStyle",
      "do_objectID": "E65EA1C6-8E7E-4C53-B718-806A478BBDF5",
      "encodedAttributes": {
        "MSAttributedStringColorAttribute": {
          "_class": "color",
          "alpha": 1,
          "blue": 1,
          "green": 1,
          "red": 1
        },
        "MSAttributedStringFontAttribute": {
          "_class": "fontDescriptor",
          "attributes": {
            "name": "SFProDisplay-Regular",
            "size": 28
          }
        },
        "kerning": 0.3600000143051147,
        "paragraphStyle": {
          "_class": "paragraphStyle",
          "allowsDefaultTighteningForTruncation": 0,
          "maximumLineHeight": 32,
          "minimumLineHeight": 32
        }
      },
      "verticalAlignment": 0
    },
    "windingRule": 1
  },
  "textBehaviour": 0,
  "userInfo": {
    "com.animaapp.stc-sketch-plugin": {
      "kModelPropertiesKey": {
        "isAutoWidth": 1
      }
    }
  }
}