{
  "_class": "group",
  "booleanOperation": -1,
  "clippingMaskMode": 0,
  "do_objectID": "794994AC-CE55-4DB8-A57B-92AA3FF90F0B",
  "exportOptions": {
    "_class": "exportOptions",
    "exportFormats": [
    ],
    "includedLayerIds": [
    ],
    "layerOptions": 0,
    "shouldTrim": false
  },
  "frame": {
    "_class": "rect",
    "constrainProportions": false,
    "height": 24,
    "width": 24,
    "x": 0,
    "y": 0
  },
  "groupLayout": {
    "_class": "MSImmutableFreeformGroupLayout"
  },
  "hasClickThrough": false,
  "hasClippingMask": false,
  "isFixedToViewport": false,
  "isFlippedHorizontal": false,
  "isFlippedVertical": false,
  "isLocked": false,
  "isVisible": true,
  "layerListExpandedType": 0,
  "layers": [
    {
      "class": "group",
      "id": "CFEF1369-F825-4E18-A6EB-21D35B41BC6E"
    }
  ],
  "name": "Assets/Movistar/24/GestionTickets",
  "nameIsFixed": false,
  "resizingConstraint": 63,
  "resizingType": 0,
  "rotation": 0,
  "shouldBreakMaskChain": false,
  "style": {
    "_class": "style",
    "blur": {
      "_class": "blur",
      "center": "{0.5, 0.5}",
      "isEnabled": false,
      "motionAngle": 0,
      "radius": 10,
      "saturation": 1,
      "type": 0
    },
    "borderOptions": {
      "_class": "borderOptions",
      "dashPattern": [
      ],
      "isEnabled": true,
      "lineCapStyle": 0,
      "lineJoinStyle": 0
    },
    "borders": [
    ],
    "colorControls": {
      "_class": "colorControls",
      "brightness": 0,
      "contrast": 1,
      "hue": 0,
      "isEnabled": true,
      "saturation": 1
    },
    "contextSettings": {
      "_class": "graphicsContextSettings",
      "blendMode": 0,
      "opacity": 1
    },
    "do_objectID": "87284789-26CA-4E18-83CD-A360C884CFA0",
    "endMarkerType": 0,
    "fills": [
    ],
    "innerShadows": [
    ],
    "miterLimit": 10,
    "shadows": [
    ],
    "startMarkerType": 0,
    "windingRule": 1
  },
  "userInfo": {
    "com.bohemiancoding.sketchtool.detach": {
      "symbolInstance": {
        "do_objectID": "0AA2A50B-EA32-417B-9D5E-479834F48206",
        "frame": {
          "_class": "rect",
          "constrainProportions": false,
          "height": 24,
          "width": 24,
          "x": 0,
          "y": 0
        }
      },
      "symbolMaster": {
        "do_objectID": "F72DE3FA-5F62-42E5-8C3C-F16B55713640",
        "symbolID": "96E3C500-5B1E-43AE-81F9-C197A27721BA"
      }
    },
    "com.sketch.detach": {
      "symbolInstance": {
        "do_objectID": "0AA2A50B-EA32-417B-9D5E-479834F48206",
        "frame": {
          "_class": "rect",
          "constrainProportions": false,
          "height": 24,
          "width": 24,
          "x": 0,
          "y": 0
        }
      },
      "symbolMaster": {
        "do_objectID": "F72DE3FA-5F62-42E5-8C3C-F16B55713640",
        "symbolID": "96E3C500-5B1E-43AE-81F9-C197A27721BA"
      }
    }
  }
}