{
  "_class": "symbolMaster",
  "allowsOverrides": true,
  "backgroundColor": {
    "_class": "color",
    "alpha": 1,
    "blue": 1,
    "green": 1,
    "red": 1
  },
  "booleanOperation": -1,
  "changeIdentifier": 4048,
  "clippingMaskMode": 0,
  "do_objectID": "26053EB0-AC7A-41B9-9640-135ED35CDF33",
  "exportOptions": {
    "_class": "exportOptions",
    "exportFormats": [
    ],
    "includedLayerIds": [
    ],
    "layerOptions": 0,
    "shouldTrim": false
  },
  "frame": {
    "_class": "rect",
    "constrainProportions": false,
    "height": 116,
    "width": 360,
    "x": 14650,
    "y": 5849
  },
  "groupLayout": {
    "_class": "MSImmutableInferredGroupLayout",
    "axis": 1,
    "layoutAnchor": 0,
    "maxSize": 0,
    "minSize": 0
  },
  "hasBackgroundColor": false,
  "hasClickThrough": true,
  "hasClippingMask": false,
  "horizontalRulerData": {
    "_class": "rulerData",
    "base": 0,
    "guides": [
    ]
  },
  "includeBackgroundColorInExport": true,
  "includeBackgroundColorInInstance": false,
  "includeInCloudUpload": true,
  "isFixedToViewport": false,
  "isFlippedHorizontal": false,
  "isFlippedVertical": false,
  "isFlowHome": false,
  "isLocked": false,
  "isVisible": true,
  "layerListExpandedType": 2,
  "layers": [
    {
      "class": "rectangle",
      "id": "56F6E441-FD77-491F-BC5D-9CD758F3A470"
    },
    {
      "class": "rectangle",
      "id": "F8AE4619-CD99-4863-9B68-F5FEA3462B31"
    },
    {
      "class": "symbolInstance",
      "id": "DD9AC2BC-5986-40B0-B6A7-C4E2865CB714"
    },
    {
      "class": "symbolInstance",
      "id": "9E1C0CCA-34A2-4D40-8733-DD0DF6AEA16A"
    },
    {
      "class": "group",
      "id": "AF8C8ED8-90A1-449A-9599-DA7C66C02B80"
    },
    {
      "class": "symbolInstance",
      "id": "B007EA6A-BF1F-4419-AE75-0C43C5570A94"
    }
  ],
  "name": "Ι🔒Resources/Ι🔒D E P R E C A T E D/Banner/NoTitle/Actions",
  "nameIsFixed": true,
  "overrideProperties": [
    {
      "_class": "MSImmutableOverrideProperty",
      "canOverride": true,
      "overrideName": "26F8DF20-B5D8-4C92-85F3-F29A48806CC4_symbolID"
    },
    {
      "_class": "MSImmutableOverrideProperty",
      "canOverride": true,
      "overrideName": "B007EA6A-BF1F-4419-AE75-0C43C5570A94_symbolID"
    },
    {
      "_class": "MSImmutableOverrideProperty",
      "canOverride": true,
      "overrideName": "2DD5B405-513C-4F3D-A9BD-C23839AD195C_textStyle"
    },
    {
      "_class": "MSImmutableOverrideProperty",
      "canOverride": true,
      "overrideName": "56F6E441-FD77-491F-BC5D-9CD758F3A470_layerStyle"
    },
    {
      "_class": "MSImmutableOverrideProperty",
      "canOverride": true,
      "overrideName": "9E1C0CCA-34A2-4D40-8733-DD0DF6AEA16A_symbolID"
    },
    {
      "_class": "MSImmutableOverrideProperty",
      "canOverride": true,
      "overrideName": "DD9AC2BC-5986-40B0-B6A7-C4E2865CB714_symbolID"
    },
    {
      "_class": "MSImmutableOverrideProperty",
      "canOverride": true,
      "overrideName": "2DD5B405-513C-4F3D-A9BD-C23839AD195C_stringValue"
    }
  ],
  "presetDictionary": {
  },
  "resizesContent": true,
  "resizingConstraint": 63,
  "resizingType": 0,
  "rotation": 0,
  "shouldBreakMaskChain": true,
  "style": {
    "_class": "style",
    "blur": {
      "_class": "blur",
      "center": "{0.5, 0.5}",
      "isEnabled": false,
      "motionAngle": 0,
      "radius": 10,
      "saturation": 1,
      "type": 0
    },
    "borderOptions": {
      "_class": "borderOptions",
      "dashPattern": [
      ],
      "isEnabled": true,
      "lineCapStyle": 0,
      "lineJoinStyle": 0
    },
    "borders": [
    ],
    "colorControls": {
      "_class": "colorControls",
      "brightness": 0,
      "contrast": 1,
      "hue": 0,
      "isEnabled": true,
      "saturation": 1
    },
    "contextSettings": {
      "_class": "graphicsContextSettings",
      "blendMode": 0,
      "opacity": 1
    },
    "do_objectID": "4034CB04-2F3E-4EC0-94F9-EB36A5C89E66",
    "endMarkerType": 0,
    "fills": [
    ],
    "innerShadows": [
    ],
    "miterLimit": 10,
    "shadows": [
    ],
    "startMarkerType": 0,
    "windingRule": 1
  },
  "symbolID": "8666097F-47AA-4249-BCF9-5848FC890EBF",
  "verticalRulerData": {
    "_class": "rulerData",
    "base": 0,
    "guides": [
    ]
  }
}