{
  "_class": "shapePath",
  "booleanOperation": -1,
  "clippingMaskMode": 0,
  "do_objectID": "1E18CEA3-BFBD-4951-9824-2EE0E4750D3B",
  "edited": true,
  "exportOptions": {
    "_class": "exportOptions",
    "exportFormats": [
    ],
    "includedLayerIds": [
    ],
    "layerOptions": 0,
    "shouldTrim": false
  },
  "frame": {
    "_class": "rect",
    "constrainProportions": false,
    "height": 8.48946504104595,
    "width": 4.10983982709697,
    "x": 170.2276980568621,
    "y": 21.88739529414958
  },
  "hasClippingMask": false,
  "isClosed": true,
  "isFixedToViewport": false,
  "isFlippedHorizontal": false,
  "isFlippedVertical": false,
  "isLocked": false,
  "isVisible": true,
  "layerListExpandedType": 0,
  "maintainScrollPosition": false,
  "name": "Fill 459",
  "nameIsFixed": false,
  "pointRadiusBehaviour": 1,
  "points": [
    {
      "_class": "curvePoint",
      "cornerRadius": 0,
      "curveFrom": "{0.42879781528789845, 0.99322459627379056}",
      "curveMode": 4,
      "curveTo": "{1.0000000000000027, 1}",
      "hasCurveFrom": true,
      "hasCurveTo": false,
      "point": "{1.0000000000000027, 1}"
    },
    {
      "_class": "curvePoint",
      "cornerRadius": 0,
      "curveFrom": "{0.08603431818406912, 0.65753413892978751}",
      "curveMode": 4,
      "curveTo": "{0.12083799635153318, 0.84704012799921558}",
      "hasCurveFrom": false,
      "hasCurveTo": true,
      "point": "{0.08603431818406912, 0.65753413892978751}"
    },
    {
      "_class": "curvePoint",
      "cornerRadius": 0,
      "curveFrom": "{-0.001080342926014118, 0.18068943728975953}",
      "curveMode": 4,
      "curveTo": "{0.002505490582148156, 0.20029704504288043}",
      "hasCurveFrom": true,
      "hasCurveTo": false,
      "point": "{0.002505490582148156, 0.20029704504288043}"
    },
    {
      "_class": "curvePoint",
      "cornerRadius": 0,
      "curveFrom": "{0.10776025061588289, 0.083780632478524228}",
      "curveMode": 4,
      "curveTo": "{-0.00044754877751171937, 0.1612871448010702}",
      "hasCurveFrom": true,
      "hasCurveTo": true,
      "point": "{0.0020836278164858856, 0.14219282520902526}"
    },
    {
      "_class": "curvePoint",
      "cornerRadius": 0,
      "curveFrom": "{0.64204944333218761, -0.020211548955565015}",
      "curveMode": 3,
      "curveTo": "{0.2611073659355661, 0.036250148762844943}",
      "hasCurveFrom": true,
      "hasCurveTo": true,
      "point": "{0.46423428760386487, 0.0060688048915495986}"
    },
    {
      "_class": "curvePoint",
      "cornerRadius": 0,
      "curveFrom": "{0.8415905314923241, 0.13213237725192684}",
      "curveMode": 4,
      "curveTo": "{0.82492695224850554, 0.041998976166900993}",
      "hasCurveFrom": false,
      "hasCurveTo": true,
      "point": "{0.8415905314923241, 0.13213237725192684}"
    }
  ],
  "resizingConstraint": 63,
  "resizingType": 0,
  "rotation": 0,
  "shouldBreakMaskChain": false,
  "style": {
    "_class": "style",
    "blur": {
      "_class": "blur",
      "center": "{0.5, 0.5}",
      "isEnabled": false,
      "motionAngle": 0,
      "radius": 8.668941979522186,
      "saturation": 1,
      "type": 0
    },
    "borderOptions": {
      "_class": "borderOptions",
      "dashPattern": [
      ],
      "isEnabled": true,
      "lineCapStyle": 0,
      "lineJoinStyle": 0
    },
    "borders": [
    ],
    "colorControls": {
      "_class": "colorControls",
      "brightness": 0,
      "contrast": 1,
      "hue": 0,
      "isEnabled": true,
      "saturation": 1
    },
    "contextSettings": {
      "_class": "graphicsContextSettings",
      "blendMode": 0,
      "opacity": 1
    },
    "do_objectID": "8AD72B1A-0AB9-48E3-BF5D-43DCA244D258",
    "endMarkerType": 0,
    "fills": [
      {
        "_class": "fill",
        "color": {
          "_class": "color",
          "alpha": 1,
          "blue": 0.5134755969047546,
          "green": 0.2508316934108734,
          "red": 0.02695708908140659
        },
        "contextSettings": {
          "_class": "graphicsContextSettings",
          "blendMode": 0,
          "opacity": 1
        },
        "fillType": 0,
        "gradient": {
          "_class": "gradient",
          "elipseLength": 0,
          "from": "{0.5, 0}",
          "gradientType": 0,
          "stops": [
            {
              "_class": "gradientStop",
              "color": {
                "_class": "color",
                "alpha": 1,
                "blue": 1,
                "green": 1,
                "red": 1
              },
              "position": 0
            },
            {
              "_class": "gradientStop",
              "color": {
                "_class": "color",
                "alpha": 1,
                "blue": 0,
                "green": 0,
                "red": 0
              },
              "position": 1
            }
          ],
          "to": "{0.5, 1}"
        },
        "isEnabled": true,
        "noiseIndex": 0,
        "noiseIntensity": 0,
        "patternFillType": 1,
        "patternTileScale": 1
      }
    ],
    "innerShadows": [
    ],
    "miterLimit": 10,
    "shadows": [
    ],
    "startMarkerType": 0,
    "windingRule": 1
  }
}