{
  "_class": "shapePath",
  "booleanOperation": -1,
  "clippingMaskMode": 0,
  "do_objectID": "6C709BC1-F16F-415F-92F4-21E1E59A089F",
  "edited": true,
  "exportOptions": {
    "_class": "exportOptions",
    "exportFormats": [
    ],
    "includedLayerIds": [
    ],
    "layerOptions": 0,
    "shouldTrim": false
  },
  "frame": {
    "_class": "rect",
    "constrainProportions": false,
    "height": 15.044,
    "width": 22.723,
    "x": 0,
    "y": 0
  },
  "hasClippingMask": false,
  "isClosed": true,
  "isFixedToViewport": false,
  "isFlippedHorizontal": false,
  "isFlippedVertical": false,
  "isLocked": false,
  "isVisible": true,
  "layerListExpandedType": 0,
  "maintainScrollPosition": false,
  "name": "Path",
  "nameIsFixed": false,
  "pointRadiusBehaviour": 1,
  "points": [
    {
      "_class": "curvePoint",
      "cornerRadius": 0,
      "curveFrom": "{0.38414821986533476, 0.41870513161393241}",
      "curveMode": 4,
      "curveTo": "{0.37455441623025137, 0.43273065674022865}",
      "hasCurveFrom": true,
      "hasCurveTo": false,
      "point": "{0.37455441623025137, 0.43273065674022865}"
    },
    {
      "_class": "curvePoint",
      "cornerRadius": 0,
      "curveFrom": "{0.41002508471592664, 0.42741292209518744}",
      "curveMode": 4,
      "curveTo": "{0.39880297495929234, 0.41644509438978988}",
      "hasCurveFrom": false,
      "hasCurveTo": true,
      "point": "{0.41002508471592664, 0.42741292209518744}"
    },
    {
      "_class": "curvePoint",
      "cornerRadius": 0,
      "curveFrom": "{0.99881177661400355, 0.98504387131082149}",
      "curveMode": 4,
      "curveTo": "{0.99691942085111995, 0.99999999999999989}",
      "hasCurveFrom": true,
      "hasCurveTo": false,
      "point": "{0.99691942085111995, 0.99999999999999989}"
    },
    {
      "_class": "curvePoint",
      "cornerRadius": 0,
      "curveFrom": "{1, 0.95380218027120434}",
      "curveMode": 4,
      "curveTo": "{1, 0.96962244084020188}",
      "hasCurveFrom": false,
      "hasCurveTo": true,
      "point": "{1, 0.95380218027120434}"
    },
    {
      "_class": "curvePoint",
      "cornerRadius": 0,
      "curveFrom": "{1, 0.10881414517415582}",
      "curveMode": 4,
      "curveTo": "{1, 0.2426216431800054}",
      "hasCurveFrom": true,
      "hasCurveTo": false,
      "point": "{1, 0.2426216431800054}"
    },
    {
      "_class": "curvePoint",
      "cornerRadius": 0,
      "curveFrom": "{0.83932579324913081, 0}",
      "curveMode": 4,
      "curveTo": "{0.92791444791620836, 0}",
      "hasCurveFrom": false,
      "hasCurveTo": true,
      "point": "{0.83932579324913081, 0}"
    },
    {
      "_class": "curvePoint",
      "cornerRadius": 0,
      "curveFrom": "{0.072085552083791832, 0}",
      "curveMode": 4,
      "curveTo": "{0.16067420675086916, 0}",
      "hasCurveFrom": true,
      "hasCurveTo": false,
      "point": "{0.16067420675086916, 0}"
    },
    {
      "_class": "curvePoint",
      "cornerRadius": 0,
      "curveFrom": "{0, 0.2426216431800054}",
      "curveMode": 4,
      "curveTo": "{0, 0.10881414517415582}",
      "hasCurveFrom": false,
      "hasCurveTo": true,
      "point": "{0, 0.2426216431800054}"
    },
    {
      "_class": "curvePoint",
      "cornerRadius": 0,
      "curveFrom": "{0, 0.96284232916777435}",
      "curveMode": 4,
      "curveTo": "{0, 0.95380218027120434}",
      "hasCurveFrom": true,
      "hasCurveTo": false,
      "point": "{0, 0.95380218027120434}"
    },
    {
      "_class": "curvePoint",
      "cornerRadius": 0,
      "curveFrom": "{0.0017603309422170993, 0.98025791013028429}",
      "curveMode": 4,
      "curveTo": "{0.0011442151124411303, 0.97141717628290336}",
      "hasCurveFrom": false,
      "hasCurveTo": true,
      "point": "{0.0017603309422170993, 0.98025791013028429}"
    }
  ],
  "resizingConstraint": 63,
  "resizingType": 0,
  "rotation": 0,
  "shouldBreakMaskChain": false,
  "style": {
    "_class": "style",
    "blur": {
      "_class": "blur",
      "center": "{0.5, 0.5}",
      "isEnabled": false,
      "motionAngle": 0,
      "radius": 10,
      "saturation": 1,
      "type": 0
    },
    "borderOptions": {
      "_class": "borderOptions",
      "dashPattern": [
      ],
      "isEnabled": true,
      "lineCapStyle": 0,
      "lineJoinStyle": 0
    },
    "borders": [
    ],
    "colorControls": {
      "_class": "colorControls",
      "brightness": 0,
      "contrast": 1,
      "hue": 0,
      "isEnabled": true,
      "saturation": 1
    },
    "contextSettings": {
      "_class": "graphicsContextSettings",
      "blendMode": 0,
      "opacity": 1
    },
    "do_objectID": "F665CF29-A056-48DB-8BBC-331AF787BAF4",
    "endMarkerType": 0,
    "fills": [
    ],
    "innerShadows": [
    ],
    "miterLimit": 10,
    "shadows": [
    ],
    "startMarkerType": 0,
    "windingRule": 1
  }
}